LICENSE
MANIFEST.in
README.md
pyproject.toml
setup.py
damegender.egg-info/PKG-INFO
damegender.egg-info/SOURCES.txt
damegender.egg-info/dependency_links.txt
damegender.egg-info/entry_points.txt
damegender.egg-info/not-zip-safe
damegender.egg-info/requires.txt
damegender.egg-info/top_level.txt
src/damegender/GPL.txt
src/damegender/README.md
src/damegender/accuracy.py
src/damegender/api2gender.py
src/damegender/apikeyadd.py
src/damegender/checkcsv.py
src/damegender/config.cfg
src/damegender/config.enabled.cfg
src/damegender/confusion.py
src/damegender/corr.py
src/damegender/csv2gender.py
src/damegender/csv2jsonapirest.py
src/damegender/damegender2json.py
src/damegender/downloadcsv.py
src/damegender/downloadjson.py
src/damegender/errors.py
src/damegender/ethnicity.py
src/damegender/get-wikidata-names.py
src/damegender/get-wikidata-surnames.py
src/damegender/git2gender.py
src/damegender/infofeatures.py
src/damegender/jokes.py
src/damegender/launchpad2gender.py
src/damegender/mail2gender.py
src/damegender/main.py
src/damegender/mergeinterfiles.py
src/damegender/nameincountries.py
src/damegender/newspaper2gender.py
src/damegender/orig2.py
src/damegender/pca-components.py
src/damegender/pca-features.py
src/damegender/percentage2names.py
src/damegender/postinstall.py
src/damegender/roc.py
src/damegender/startwith.py
src/damegender/surname.py
src/damegender/surnameincountries.py
src/damegender/top.py
src/damegender/app/__init__.py
src/damegender/app/dame_brazilapi.py
src/damegender/app/dame_ethnicity.py
src/damegender/app/dame_gender.py
src/damegender/app/dame_genderapi.py
src/damegender/app/dame_genderguesser.py
src/damegender/app/dame_genderize.py
src/damegender/app/dame_nameapi.py
src/damegender/app/dame_namsor.py
src/damegender/app/dame_perceval.py
src/damegender/app/dame_sexmachine.py
src/damegender/app/dame_standards.py
src/damegender/app/dame_statistics.py
src/damegender/app/dame_utils.py
src/damegender/app/dame_wikidata.py
src/damegender/files/__init__.py
src/damegender/files/features_list.csv
src/damegender/files/features_list_cat.csv
src/damegender/files/features_list_no_cat.csv
src/damegender/files/features_list_no_undefined.csv
src/damegender/files/forbes2020.csv
