Metadata-Version: 2.1
Name: damegender
Version: 0.5.6.post2
Summary: Gender Detection Tool by David Arroyo MEnéndez
Home-page: http://github.com/davidam/damegender
Author: David Arroyo Menéndez
Author-email: David Arroyo Menéndez <davidam@gmail.com>
Maintainer-email: David Arroyo Menéndez <davidam@gmail.com>
License:                     GNU GENERAL PUBLIC LICENSE
Project-URL: Homepage, https://damegender.davidam.com
Project-URL: Bug Reports, https://github.com/davidam/damegender/issues
Project-URL: Funding, https://www.paypal.com/donate/?cmd=_donations&business=davidam%40gmail.com&currency_code=EUR&amount=10&source=url
Project-URL: Say Thanks!, https://github.com/davidam/damegender/wiki
Project-URL: Source, https://github.com/davidam/damegender/
Keywords: dame,gender,name,gender detection,development
Classifier: Development Status :: 3 - Alpha
Classifier: Intended Audience :: Developers
Classifier: Topic :: Software Development :: Build Tools
Classifier: License :: OSI Approved :: GNU General Public License v3 (GPLv3)
Classifier: Programming Language :: Python :: 3
Classifier: Programming Language :: Python :: 3.7
Classifier: Programming Language :: Python :: 3.8
Classifier: Programming Language :: Python :: 3.9
Classifier: Programming Language :: Python :: 3.10
Classifier: Programming Language :: Python :: 3.11
Classifier: Programming Language :: Python :: 3 :: Only
Requires-Python: >3.6
License-File: LICENSE
Requires-Dist: nltk
Requires-Dist: numpy
Requires-Dist: requests
Requires-Dist: scikit-learn
Requires-Dist: unidecode
Requires-Dist: pandas
Requires-Dist: matplotlib
Requires-Dist: json2html
Provides-Extra: mails-and-repositories
Requires-Dist: perceval; extra == "mails-and-repositories"
Provides-Extra: apis
Requires-Dist: genderize; extra == "apis"
Provides-Extra: all
Requires-Dist: perceval; extra == "all"
Requires-Dist: genderize; extra == "all"
Requires-Dist: scikit-learn; extra == "all"
Provides-Extra: all-extended
Requires-Dist: perceval; extra == "all-extended"
Requires-Dist: gender_guesser; extra == "all-extended"
Requires-Dist: genderize; extra == "all-extended"
Requires-Dist: newspaper3k; extra == "all-extended"
Requires-Dist: scikit-learn; extra == "all-extended"
Requires-Dist: transliterate; extra == "all-extended"
